LICENSE
MANIFEST.in
README.rst
requirements.txt
setup.cfg
setup.py
versioneer.py
exconfig/__init__.py
exconfig/_version.py
exconfig/configuration.py
exconfig/errors.py
exconfig/field.py
exconfig/validators.py
exconfig.egg-info/PKG-INFO
exconfig.egg-info/SOURCES.txt
exconfig.egg-info/dependency_links.txt
exconfig.egg-info/requires.txt
exconfig.egg-info/top_level.txt