Metadata-Version: 1.1
Name: exconfig
Version: 0.2.0
Summary: Configuration
Home-page: http://csdms.colorado.edu
Author: Eric Hutton
Author-email: huttone@colorado.edu
License: UNKNOWN
Platform: UNKNOWN
Classifier: Intended Audience :: Science/Research
Classifier: License :: OSI Approved :: MIT License
Classifier: Operating System :: OS Independent
Classifier: Programming Language :: Python :: 3.6
Classifier: Programming Language :: Python :: 3.7
Classifier: Programming Language :: Python :: 3.8
Classifier: Topic :: Scientific/Engineering :: Physics
